bluetooth_2_usb/__init__.py
bluetooth_2_usb/args.py
bluetooth_2_usb/evdev.py
bluetooth_2_usb/logging.py
bluetooth_2_usb/relay.py
bluetooth_2_usb-0.9.1.dist-info/LICENSE
bluetooth_2_usb-0.9.1.dist-info/METADATA
bluetooth_2_usb-0.9.1.dist-info/WHEEL
bluetooth_2_usb-0.9.1.dist-info/top_level.txt
bluetooth_2_usb-0.9.1.dist-info/RECORD
