Metadata-Version: 2.2
Name: bluetooth_2_usb
Version: 0.9.1
Summary: Convert a Raspberry Pi into a HID relay translating Bluetooth keyboard and mouse input to USB.
Author-email: quaxalber <pypi@quaxalber.de>
License: MIT
Project-URL: Homepage, https://github.com/quaxalber/bluetooth_2_usb
Project-URL: Issues, https://github.com/quaxalber/bluetooth_2_usb/issues
Keywords: adapter,proxy,relay,bluetooth,usb,hid,human,interface,device,keyboard,mouse,consumer,keycode,keypadhardware,raspberry,evdev
Classifier: Programming Language :: Python :: 3
Classifier: Programming Language :: Python :: 3.11
Classifier: License :: OSI Approved :: MIT License
Classifier: Operating System :: POSIX :: Linux
Classifier: Topic :: System :: Hardware :: Universal Serial Bus (USB) :: Human Interface Device (HID)
Classifier: Intended Audience :: Developers
Classifier: Intended Audience :: End Users/Desktop
Classifier: Development Status :: 3 - Alpha
Requires-Python: >=3.11
License-File: LICENSE
Requires-Dist: adafruit-circuitpython-typing==1.2.0
Requires-Dist: Adafruit-PlatformDetect==3.57.0
Requires-Dist: Adafruit-PureIO==1.1.11
Requires-Dist: evdev==1.6.1
Requires-Dist: pyftdi==0.55.0
Requires-Dist: pyserial==3.5
Requires-Dist: pyudev==0.24.3
Requires-Dist: pyusb==1.2.1
Requires-Dist: quax-Blinka==8.27.0.post2
Requires-Dist: quax-circuitpython-hid==6.0.2.post1
Requires-Dist: rpi-ws281x==5.0.0
Requires-Dist: RPi.GPIO==0.7.1
Requires-Dist: sysv-ipc==1.1.0
